Metadata-Version: 2.1
Name: Perceptron-pypi-prayaspatnaik21
Version: 0.0.2
Summary: A Perceptron package
Home-page: https://github.com/prayaspatnaik21/Perceptron_pypi
Author: prayaspatnaik21
Author-email: prayaspatnaik21@gmail.com
License: UNKNOWN
Project-URL: Bug Tracker, https://github.com/{USER_NAME}/{PROJECT_NAME}/issues
Platform: UNKNOWN
Classifier: Programming Language :: Python :: 3
Classifier: License :: OSI Approved :: MIT License
Classifier: Operating System :: OS Independent
Requires-Python: >=3.7
License-File: LICENSE
Requires-Dist: numpy
Requires-Dist: tqdm
